conda/anaconda_deploy.sh
conda/meta.yaml
docs/Makefile
docs/_config.yml
docs/index.md
docs/requirements.txt
docs/notebook/lib-usage.ipynb
docs/source/cli-usage.rst
docs/source/conf.py
docs/source/conf.py.tmpl
docs/source/endmatter.rst
docs/source/examples.rst
docs/source/index.rst
docs/source/intro.rst
docs/source/lib-usage.rst
docs/source/modules.rst
docs/source/_static/favicon.ico
docs/source/_templates/layout.html
docs/source/fig/favicon.ico
docs/source/fig/favicon.png
docs/source/fig/favicon.svg
docs/source/fig/plot1.pdf
docs/source/fig/plot1.png
docs/source/fig/plot1.svg
docs/source/fig/plot2.pdf
docs/source/fig/plot2.png
docs/source/fig/plot2.svg
docs/source/fig/plot3.pdf
docs/source/fig/plot3.png
docs/source/fig/plot3.svg
docs/source/fig/plot3a.pdf
docs/source/fig/plot3a.png
docs/source/fig/plot3a.svg
docs/source/fig/plot3b.pdf
docs/source/fig/plot3b.png
docs/source/fig/plot3b.svg
docs/source/lib-usage_files/lib-usage_12_1.png
docs/source/lib-usage_files/lib-usage_18_1.png
docs/source/lib-usage_files/lib-usage_9_1.png
elastic/__init__.py
elastic/_version.py
elastic/elastic.py
elastic/cli/__init__.py
elastic/cli/elastic.py
examples/example1.py
examples/example2.py
examples/example3.py
examples/scripts/check-job
examples/scripts/run-on-tsi
examples/scripts/run-vasp5-lock
examples/scripts/run_vasp.py
parcalc/__init__.py
parcalc/parcalc.py
test/test_elastic.py
tests/runtest.sh
tests/test_01.py
tests/test_02.py
tests/test_elastic.py
tests/data/INCAR
tests/data/KPOINTS
tests/data/POSCAR
tests/data/POTCAR
tests/data/abinit
tests/data/cij_000.POSCAR
tests/data/cij_001.POSCAR
tests/data/cij_002.POSCAR
tests/data/cij_003.POSCAR
tests/data/cij_004.POSCAR
tests/data/cij_005.POSCAR
tests/data/cij_006.POSCAR
tests/data/cij_007.POSCAR
tests/data/cij_008.POSCAR
tests/data/cij_009.POSCAR
tests/data/cij_010.POSCAR
tests/data/eos_000.POSCAR
tests/data/eos_001.POSCAR
tests/data/eos_002.POSCAR
tests/data/eos_003.POSCAR
tests/data/eos_004.POSCAR
tests/data/eos_005.POSCAR
elastic-5.2.5.2.dist-info/LICENSE
elastic-5.2.5.2.dist-info/METADATA
elastic-5.2.5.2.dist-info/WHEEL
elastic-5.2.5.2.dist-info/entry_points.txt
elastic-5.2.5.2.dist-info/top_level.txt
elastic-5.2.5.2.dist-info/RECORD
