Metadata-Version: 2.1
Name: elastic
Version: 5.2.5.2
Summary: Extension for ASE to calculate elastic constants
Author-email: "Paweł T. Jochym" <Pawel.Jochym@ifj.edu.pl>, Georgios Tritsaris <gtritsaris@seas.harvard.edu>
Maintainer-email: "Paweł T. Jochym" <Pawel.Jochym@ifj.edu.pl>
License: GPLv3
Project-URL: Homepage, https://wolf.ifj.edu.pl/elastic
Project-URL: Documentation, http://elastic.rtfd.org/
Project-URL: Repository, https://github.com/jochym/Elastic
Project-URL: Issues, https://github.com/jochym/Elastic/issues
Project-URL: Changelog, https://github.com/jochym/Elastic/blob/master/CHANGELOG.md
Keywords: science,physics,ase,elastic constants,crystals
Classifier: Development Status :: 5 - Production/Stable
Classifier: License :: OSI Approved :: GNU General Public License v3 or later (GPLv3+)
Classifier: Programming Language :: Python :: 3
License-File: LICENSE
Requires-Dist: ase
Requires-Dist: spglib
Requires-Dist: numpy
Requires-Dist: scipy
Requires-Dist: click
